banglanlp/__init__.py
banglanlp/output.py
banglanlp/rootfinder.py
banglanlp/data/dictঅ.json
banglanlp/data/dictআ.json
banglanlp/data/dictই.json
banglanlp/data/dictঈ.json
banglanlp/data/dictউ.json
banglanlp/data/dictঊ.json
banglanlp/data/dictঋ.json
banglanlp/data/dictএ.json
banglanlp/data/dictঐ.json
banglanlp/data/dictও.json
banglanlp/data/dictঔ.json
banglanlp/data/dictক.json
banglanlp/data/dictখ.json
banglanlp/data/dictগ.json
banglanlp/data/dictঘ.json
banglanlp/data/dictঙ.json
banglanlp/data/dictচ.json
banglanlp/data/dictছ.json
banglanlp/data/dictজ.json
banglanlp/data/dictঝ.json
banglanlp/data/dictঞ.json
banglanlp/data/dictট.json
banglanlp/data/dictঠ.json
banglanlp/data/dictড.json
banglanlp/data/dictঢ.json
banglanlp/data/dictঢ়.json
banglanlp/data/dictণ.json
banglanlp/data/dictত.json
banglanlp/data/dictথ.json
banglanlp/data/dictদ.json
banglanlp/data/dictধ.json
banglanlp/data/dictন.json
banglanlp/data/dictপ.json
banglanlp/data/dictফ.json
banglanlp/data/dictব.json
banglanlp/data/dictভ.json
banglanlp/data/dictম.json
banglanlp/data/dictয.json
banglanlp/data/dictর.json
banglanlp/data/dictল.json
banglanlp/data/dictশ.json
banglanlp/data/dictষ.json
banglanlp/data/dictস.json
banglanlp/data/dictহ.json
banglanlp/data/dictড়.json
banglanlp/data/dictয়.json
banglanlp/data/latter_uniqueness.json
test/__init__.py
test/test_stem.py
banglanlp-0.1.5.dist-info/LICENSE.txt
banglanlp-0.1.5.dist-info/METADATA
banglanlp-0.1.5.dist-info/WHEEL
banglanlp-0.1.5.dist-info/top_level.txt
banglanlp-0.1.5.dist-info/RECORD
